pyrecipes/__init__.py
pyrecipes/chapter.py
pyrecipes/cookbook.py
pyrecipes/errors.py
pyrecipes/recipe.py
pyrecipes/cli/__init__.py
pyrecipes/cli/chapters.py
pyrecipes/cli/create.py
pyrecipes/cli/ls.py
pyrecipes/cli/run.py
pyrecipes/cli/search.py
pyrecipes/cli/show.py
pyrecipes/cli/template.py
pyrecipes/recipes/__init__.py
pyrecipes/recipes/01_data_structures_and_algorithms/01_unpacking_a_sequence_into_separate_variables/example.py
pyrecipes/recipes/01_data_structures_and_algorithms/02_unpacking_elements_from_iterables_of_arbitrary_length/example.py
pyrecipes/recipes/01_data_structures_and_algorithms/03_keep_last_n_items/example.py
pyrecipes/recipes/01_data_structures_and_algorithms/03_keep_last_n_items/somefile.txt
pyrecipes/recipes/01_data_structures_and_algorithms/04_finding_largest_or_smallest_n_items/example.py
pyrecipes/recipes/01_data_structures_and_algorithms/05_implementing_a_priority_queue/example.py
pyrecipes/recipes/01_data_structures_and_algorithms/06_mapping_keys_to_multiple_values_in_a_dictionary/example.py
pyrecipes/recipes/01_data_structures_and_algorithms/07_keeping_dictionaries_in_order/example.py
pyrecipes/recipes/01_data_structures_and_algorithms/08_calculating_with_dictionaries/example.py
pyrecipes/recipes/01_data_structures_and_algorithms/09_finding_commonalities_between_two_dictionaries/example.py
pyrecipes/recipes/01_data_structures_and_algorithms/10_removing_duplicates_from_a_sequence_while_maintaining_order/example.py
pyrecipes/recipes/01_data_structures_and_algorithms/11_naming_a_slice/example.py
pyrecipes/recipes/01_data_structures_and_algorithms/12_determining_the_most_frequently_occurring_items_in_a_sequence/example.py
pyrecipes/recipes/01_data_structures_and_algorithms/13_sorting_a_list_of_dictionaries_by_a_common_key/example.py
pyrecipes/recipes/01_data_structures_and_algorithms/14_sorting_objects_without_native_comparison_support/example.py
pyrecipes-0.3.2.dist-info/LICENSE
pyrecipes-0.3.2.dist-info/METADATA
pyrecipes-0.3.2.dist-info/WHEEL
pyrecipes-0.3.2.dist-info/entry_points.txt
pyrecipes-0.3.2.dist-info/top_level.txt
pyrecipes-0.3.2.dist-info/RECORD
