Metadata-Version: 2.1
Name: pyrecipes
Version: 0.3.2
Summary: A CLI tool to display useful Python recipes.
Author-email: Chris Adams <cfh1990@msn.com>
License: MIT
Project-URL: Homepage, https://pypi.org/project/pyrecipes/
Project-URL: Repository, https://github.com/ChrisA87/pyrecipes
Classifier: Programming Language :: Python :: 3.7
Classifier: Programming Language :: Python :: 3.8
Classifier: Programming Language :: Python :: 3.9
Classifier: Programming Language :: Python :: 3.10
Classifier: Programming Language :: Python :: 3.11
Classifier: License :: OSI Approved :: MIT License
Requires-Python: >=3.7
License-File: LICENSE
Requires-Dist: requests >=2.31
Requires-Dist: click
Requires-Dist: colorama
Requires-Dist: numpy
Requires-Dist: pytz
